lim/__init__.py
lim/genetics/__init__.py
lim/genetics/background.py
lim/genetics/heritability/__init__.py
lim/genetics/heritability/_estimate.py
lim/genetics/heritability/test/test_heritability.py
lim/genetics/model/__init__.py
lim/genetics/model/binomial.py
lim/genetics/model/canonical.py
lim/genetics/model/model.py
lim/genetics/model/normal.py
lim/genetics/phenotype/__init__.py
lim/genetics/phenotype/bernoulli.py
lim/genetics/phenotype/binomial.py
lim/genetics/phenotype/normal.py
lim/genetics/phenotype/poisson.py
lim/genetics/qtl/__init__.py
lim/genetics/qtl/_qtl.py
lim/genetics/qtl/_scan.py
lim/genetics/qtl/view.py
lim/genetics/qtl/test/test_qtl.py
lim/genetics/variance/__init__.py
lim/genetics/variance/decomposition.py
lim/random/__init__.py
lim/random/canonical.py
lim/random/fastlmm.py
lim/random/glmm.py
lim/random/regression.py
lim/random/test/test_sampling.py
lim/tool/__init__.py
lim/tool/kinship.py
lim/tool/normalize.py
lim/tool/test/test_normalize.py
lim/util/__init__.py
lim/util/fruits.py
lim/util/preprocess.py
lim/util/quantile_summary.py
lim/util/six.py
lim/util/symbol.py
lim/util/transformation.py
lim/util/type.py
lim/util/test/test_preprocess.py
lim-1.2.8.dist-info/DESCRIPTION.rst
lim-1.2.8.dist-info/METADATA
lim-1.2.8.dist-info/RECORD
lim-1.2.8.dist-info/WHEEL
lim-1.2.8.dist-info/metadata.json
lim-1.2.8.dist-info/top_level.txt
lim-1.2.8.dist-info/zip-safe
