Metadata-Version: 2.0
Name: lim
Version: 1.2.8
Summary: Lim.
Home-page: https://github.com/glimix/lim
Author: Limix Developers
Author-email: horta@ebi.ac.uk
License: MIT
Platform: UNKNOWN
Classifier: Development Status :: 5 - Production/Stable
Classifier: License :: OSI Approved :: MIT License
Classifier: Programming Language :: Python :: 2.7
Classifier: Programming Language :: Python :: 3.5
Classifier: Operating System :: OS Independent
Requires-Dist: cachetools (>=2.0)
Requires-Dist: cffi (>=1.7)
Requires-Dist: h5py
Requires-Dist: limix-inference (>=1.0.15)
Requires-Dist: numpy
Requires-Dist: numpy-sugar
Requires-Dist: optimix
Requires-Dist: pandas
Requires-Dist: pytest (>=2.9)
Requires-Dist: scipy
Requires-Dist: six
Requires-Dist: tabulate (>=0.7)
Requires-Dist: tqdm
